picoredis.py
picoredis-0.1.1.dist-info/DESCRIPTION.rst
picoredis-0.1.1.dist-info/METADATA
picoredis-0.1.1.dist-info/RECORD
picoredis-0.1.1.dist-info/WHEEL
picoredis-0.1.1.dist-info/metadata.json
picoredis-0.1.1.dist-info/top_level.txt
picoredis-0.1.1.dist-info/zip-safe
